async_scrape/__init__.py
async_scrape/libs/async_scrape.py
async_scrape/libs/base_scrape.py
async_scrape/libs/scrape.py
async_scrape/utils/errors.py
async_scrape/utils/header_vars.py
async_scrape/utils/soup.py
async_scrape-0.1.20.dist-info/METADATA
async_scrape-0.1.20.dist-info/WHEEL
async_scrape-0.1.20.dist-info/RECORD
