Metadata-Version: 2.1
Name: async-scrape
Version: 0.1.20
Summary: A package designed to scrape webpages using aiohttp and asyncio. Has some error handling to overcome common issues such as sites blocking you after n requests over a short period.
Home-page: https://github.com/cia05rf/async-scrape/
License: MIT
Keywords: scraping,async,requests
Author: Robert Franklin
Author-email: cia05rf@gmail.com
Maintainer: Robert Franklin
Maintainer-email: cia05rf@gmail.com
Requires-Python: >=3.11,<4.0
Classifier: License :: OSI Approved :: MIT License
Classifier: Programming Language :: Python :: 3
Classifier: Programming Language :: Python :: 3.11
Classifier: Programming Language :: Python :: 3.12
Classifier: Programming Language :: Python :: 3.13
Requires-Dist: aiohttp (>=3.9.5,<4.0.0)
Requires-Dist: brotli (>=1.1.0,<2.0.0)
Requires-Dist: lxml-html-clean (>=0.1.1,<0.2.0)
Requires-Dist: nest-asyncio (>=1.6.0,<2.0.0)
Requires-Dist: pypac (>=0.16.4,<0.17.0)
Requires-Dist: requests-html (>=0.10.0,<0.11.0)
Project-URL: Documentation, https://github.com/cia05rf/async-scrape/
Project-URL: Repository, https://github.com/cia05rf/async-scrape/
